ChangeLog
MANIFEST.in
README.md
README.rst
popHead
popRandom
popRange
popTail
popThese
setup.py
PopLines/__init__.py
doc/PopLines.html
doc/index.html
popLines.egg-info/PKG-INFO
popLines.egg-info/SOURCES.txt
popLines.egg-info/dependency_links.txt
popLines.egg-info/top_level.txt