Metadata-Version: 1.1
Name: popLines
Version: 2.1.0
Summary: Tools to pop/peek lines from the head/tail or known position within a given file, and output to stdout. Makes files into queues!
Home-page: https://github.com/kata198/popLines
Author: Tim Savannah
Author-email: kata198@gmail.com
License: GPLv2
Keywords: popLines,file,head,tail,random,queue,stack,pop,lines,peek,extract,text,popHead,popTail,popRandom,remove,position,line
Platform: UNKNOWN
Classifier: Development Status :: 5 - Production/Stable
Classifier: Programming Language :: Python
Classifier: License :: OSI Approved :: GNU General Public License v2 (GPLv2)
Classifier: Programming Language :: Python :: 2
Classifier: Programming Language :: Python :: 2.7
Classifier: Programming Language :: Python :: 3
Classifier: Programming Language :: Python :: 3.4
Classifier: Programming Language :: Python :: 3.5
Classifier: Programming Language :: Python :: 3.6
Classifier: Topic :: Database
Classifier: Topic :: Text Processing
Classifier: Topic :: Utilities
Provides: PopLines
